README.md
setup.py
EasyPyX.egg-info/PKG-INFO
EasyPyX.egg-info/SOURCES.txt
EasyPyX.egg-info/dependency_links.txt
EasyPyX.egg-info/requires.txt
EasyPyX.egg-info/top_level.txt
easyweb/__init__.py