Metadata-Version: 2.1
Name: EasyPyX
Version: 0.0.3
Summary: so easy
Home-page: UNKNOWN
Author: Yubadboy
Author-email: 2025677540@qq.com
License: UNKNOWN
Platform: UNKNOWN
